README.rst
setup.py
pgobserver_gatherer/__init__.py
pgobserver_gatherer/__main__.py
pgobserver_gatherer/datadb.py
pgobserver_gatherer/datastore_adapter.py
pgobserver_gatherer/delta_engine.py
pgobserver_gatherer/gatherer_base.py
pgobserver_gatherer/gatherer_bgwriter.py
pgobserver_gatherer/gatherer_connection.py
pgobserver_gatherer/gatherer_database.py
pgobserver_gatherer/gatherer_index.py
pgobserver_gatherer/gatherer_kpi.py
pgobserver_gatherer/gatherer_load.py
pgobserver_gatherer/gatherer_locks.py
pgobserver_gatherer/gatherer_schemas.py
pgobserver_gatherer/gatherer_sproc.py
pgobserver_gatherer/gatherer_statements.py
pgobserver_gatherer/gatherer_table.py
pgobserver_gatherer/gatherer_table_io.py
pgobserver_gatherer/globalconfig.py
pgobserver_gatherer/id_cache.py
pgobserver_gatherer/loader.py
pgobserver_gatherer/run.py
pgobserver_gatherer.egg-info/PKG-INFO
pgobserver_gatherer.egg-info/SOURCES.txt
pgobserver_gatherer.egg-info/dependency_links.txt
pgobserver_gatherer.egg-info/entry_points.txt
pgobserver_gatherer.egg-info/requires.txt
pgobserver_gatherer.egg-info/top_level.txt
pgobserver_gatherer/output_handlers/__init__.py
pgobserver_gatherer/output_handlers/handler_base.py
pgobserver_gatherer/output_handlers/console/__init__.py
pgobserver_gatherer/output_handlers/console/console_handler.py
pgobserver_gatherer/output_handlers/file/__init__.py
pgobserver_gatherer/output_handlers/file/file_handler.py