Metadata-Version: 1.1
Name: pgobserver-gatherer
Version: 0.1.1
Summary: PostgreSQL metrics gathering daemon
Home-page: https://github.com/zalando/PGObserver
Author: kmoppel
Author-email: kaarel.moppel@zalando.de
License: Apache License 2.0
Keywords: postgres postgresql pg database monitoring
Platform: UNKNOWN
Classifier: Development Status :: 4 - Beta
Classifier: Environment :: Console
Classifier: Intended Audience :: Developers
Classifier: Intended Audience :: System Administrators
Classifier: License :: OSI Approved :: Apache Software License
Classifier: Operating System :: POSIX :: Linux
Classifier: Programming Language :: Python
Classifier: Programming Language :: Python :: 3.4
Classifier: Programming Language :: Python :: Implementation :: CPython
Classifier: Topic :: Database
